<?xml version="1.0" encoding="utf-8" ?>
<dwsync>
<file name="arrows.gif" server="Z:/simrs/billing/" local="128441225740000000" remote="128441225740000000" />
<file name="add16.gif" server="Z:/simrs/billing/" local="129252856510000000" remote="129252856510000000" />
<file name="del16.gif" server="Z:/simrs/billing/" local="129252857530000000" remote="129252857530000000" />
<file name="back16.png" server="Z:/simrs/billing/" local="129252858920000000" remote="129252858920000000" />
<file name="view_tree16.gif" server="Z:/simrs/billing/" local="129252861410000000" remote="129252861410000000" />
<file name="view_list16.gif" server="Z:/simrs/billing/" local="129252871010000000" remote="129252871010000000" />
<file name="next.gif" server="Z:/simrs/billing/" local="127366078800000000" remote="127366078800000000" />
<file name="prev.gif" server="Z:/simrs/billing/" local="127366078320000000" remote="127366078320000000" />
<file name="page_first.gif" server="Z:/simrs/billing/" local="129206527060000000" remote="129206527060000000" />
<file name="page_prev.gif" server="Z:/simrs/billing/" local="129206527500000000" remote="129206527500000000" />
<file name="page_next.gif" server="Z:/simrs/billing/" local="129206527900000000" remote="129206527900000000" />
<file name="page_last.gif" server="Z:/simrs/billing/" local="129206528220000000" remote="129206528220000000" />
<file name="x.png" server="Z:/simrs/billing/" local="129248651760000000" remote="129248651760000000" />
</dwsync>